alppb/__init__.py
alppb/__main__.py
alppb/__version__.py
alppb/alppb.py
alppb/codebuild.py
alppb/iam.py
alppb/s3.py
tests/integration/__init__.py
tests/integration/test_create_package.py
alppb-0.4.2.dist-info/LICENSE
alppb-0.4.2.dist-info/METADATA
alppb-0.4.2.dist-info/WHEEL
alppb-0.4.2.dist-info/entry_points.txt
alppb-0.4.2.dist-info/top_level.txt
alppb-0.4.2.dist-info/RECORD
