Metadata-Version: 2.1
Name: alppb
Version: 0.4.2
Summary: Compiles Python packages on Amazon Linux to ensure their compatability when used with AWS Lambda.
Home-page: https://github.com/irlrobot/alppb/
Author: Josh Campbell
Author-email: josh@userdel.com
License: MIT
Platform: UNKNOWN
Classifier: License :: OSI Approved :: MIT License
Classifier: Programming Language :: Python
Classifier: Programming Language :: Python :: 3
Classifier: Programming Language :: Python :: 3.6
Classifier: Programming Language :: Python :: Implementation :: CPython
Classifier: Programming Language :: Python :: Implementation :: PyPy
Requires-Python: >=3.6.0
Requires-Dist: boto3
Requires-Dist: pyyaml
